mcv/__init__.py
mcv/image.py
mcv_plus-0.0.1.dist-info/METADATA
mcv_plus-0.0.1.dist-info/WHEEL
mcv_plus-0.0.1.dist-info/top_level.txt
mcv_plus-0.0.1.dist-info/RECORD
