Metadata-Version: 2.1
Name: mcv-plus
Version: 0.0.1
Summary: Opencv图像处理增强库
Author: KateTseng
Author-email: Kate.TsengK@outlook.com
License: MIT
Keywords: Auto Script Testing
Requires-Python: >=3
Requires-Dist: pillow
Requires-Dist: opencv-python
Requires-Dist: numpy
